dvg_monkeypatch_pyqtgraph.py
dvg_pyqtgraph_monkeypatch-2.0.0.dist-info/AUTHORS.rst
dvg_pyqtgraph_monkeypatch-2.0.0.dist-info/LICENSE.txt
dvg_pyqtgraph_monkeypatch-2.0.0.dist-info/METADATA
dvg_pyqtgraph_monkeypatch-2.0.0.dist-info/WHEEL
dvg_pyqtgraph_monkeypatch-2.0.0.dist-info/top_level.txt
dvg_pyqtgraph_monkeypatch-2.0.0.dist-info/RECORD
