Metadata-Version: 2.1
Name: dvg-pyqtgraph-monkeypatch
Version: 2.0.0
Summary: Monkeypatch for pyqtgraph==0.11.0 resulting in superior OpenGL performance in contrast to more recent 0.11.1 to 0.12.3
Home-page: https://github.com/Dennis-van-Gils/python-dvg-pyqtgraph-monkeypatch
Author: Dennis van Gils
Author-email: vangils.dennis@gmail.com
License: MIT
Project-URL: Issue Tracker, https://github.com/Dennis-van-Gils/python-dvg-pyqtgraph-monkeypatch/issues
Keywords: pyqtgraph,monkeypatch,chart,plot
Platform: UNKNOWN
Classifier: Development Status :: 5 - Production/Stable
Classifier: License :: OSI Approved :: MIT License
Classifier: Intended Audience :: Developers
Classifier: Intended Audience :: Science/Research
Classifier: Operating System :: OS Independent
Classifier: Programming Language :: Python
Classifier: Programming Language :: Python :: 3.6
Classifier: Programming Language :: Python :: 3.7
Classifier: Programming Language :: Python :: 3.8
Classifier: Topic :: Multimedia :: Graphics
Classifier: Topic :: Scientific/Engineering :: Visualization
Requires-Python: >=3.6
Requires-Dist: pyqtgraph (~=0.11)
